byted_operators_eo/__init__.py
byted_operators_eo-0.0.1.dist-info/METADATA
byted_operators_eo-0.0.1.dist-info/WHEEL
byted_operators_eo-0.0.1.dist-info/top_level.txt
byted_operators_eo-0.0.1.dist-info/RECORD
