Metadata-Version: 2.1
Name: byted-operators-eo
Version: 0.0.1
Summary: A simple package named byted_operators_eo
Home-page: https://github.com/artifact/byted_operators_eo.git
Author: artifact
Author-email: artifact@example.com
License: UNKNOWN
Platform: UNKNOWN
Classifier: Programming Language :: Python :: 3
Classifier: License :: OSI Approved :: MIT License
Classifier: Operating System :: OS Independent
